MANIFEST.in
README.rst
cities.gz
setup.py
fake_pyrex/Pyrex/__init__.py
fake_pyrex/Pyrex/Distutils/__init__.py
fake_pyrex/Pyrex/Distutils/build_ext.py
fuzzyset/__init__.py
fuzzyset/__init__.pyc
fuzzyset/cfuzzyset.c
fuzzyset/cfuzzyset.pyx
fuzzyset/cfuzzyset.pyx~
fuzzyset.egg-info/PKG-INFO
fuzzyset.egg-info/SOURCES.txt
fuzzyset.egg-info/dependency_links.txt
fuzzyset.egg-info/requires.txt
fuzzyset.egg-info/top_level.txt
fuzzyset/__pycache__/__init__.cpython-36.pyc
tests/interactive.py
tests/performance.py
tests/profile.py