Metadata-Version: 1.1
Name: fuzzyset
Version: 0.0.18
Summary: A simple python fuzzyset implementation.
Home-page: https://github.com/axiak/fuzzyset/
Author: Michael Axiak
Author-email: mike@axiak.net
License: BSD
Keywords: fuzzyset fuzzy data structure
Platform: UNKNOWN
Classifier: Development Status :: 3 - Alpha
Classifier: License :: OSI Approved :: BSD License
Classifier: Operating System :: OS Independent
Classifier: Programming Language :: Python
Classifier: Topic :: Software Development :: Libraries
